avalonms-0.6.0.dist-info/metadata.json
avalonms-0.6.0.dist-info/DESCRIPTION.rst
avalonms-0.6.0.dist-info/entry_points.txt
avalonms-0.6.0.dist-info/WHEEL
avalonms-0.6.0.dist-info/top_level.txt
avalonms-0.6.0.dist-info/METADATA
avalonms-0.6.0.dist-info/RECORD
avalonms-0.6.0.data/data/share/avalonms/avalon-gunicorn.py
avalonms-0.6.0.data/data/share/avalonms/avalon-supervisor-gunicorn.conf
avalonms-0.6.0.data/data/share/avalonms/avalon-supervisor-uwsgi.conf
avalonms-0.6.0.data/data/share/avalonms/avalon-uwsgi.ini
fabfile/build.py
fabfile/__init__.py
fabfile/deploy.py
avalon/settings.py
avalon/metrics.py
avalon/ids.py
avalon/models.py
avalon/log.py
avalon/cache.py
avalon/exc.py
avalon/compat.py
avalon/elms.py
avalon/util.py
avalon/__init__.py
avalon/tags/crawl.py
avalon/tags/insert.py
avalon/tags/read.py
avalon/tags/__init__.py
avalon/cli/scan.py
avalon/cli/config.py
avalon/cli/__init__.py
avalon/web/filtering.py
avalon/web/search.py
avalon/web/request.py
avalon/web/services.py
avalon/web/response.py
avalon/web/controller.py
avalon/web/__init__.py
avalon/app/factory.py
avalon/app/bootstrap.py
avalon/app/wsgi.py
avalon/app/__init__.py
avalon/packages/six.py
avalon/packages/__init__.py
