Metadata-Version: 2.0
Name: avalonms
Version: 0.6.0
Summary: Avalon Music Server
Home-page: http://www.tshlabs.org/
Author: TSH Labs
Author-email: projects@tshlabs.org
License: MIT
Platform: UNKNOWN
Classifier: Development Status :: 4 - Beta
Classifier: License :: OSI Approved :: MIT License
Classifier: Operating System :: POSIX :: BSD
Classifier: Operating System :: POSIX :: Linux
Classifier: Topic :: Internet :: WWW/HTTP
Classifier: Topic :: Multimedia :: Sound/Audio
Classifier: Programming Language :: Python
Classifier: Programming Language :: Python :: 2.6
Classifier: Programming Language :: Python :: 2.7
Classifier: Programming Language :: Python :: 3.3
Classifier: Programming Language :: Python :: 3.4
Requires-Dist: flask
Requires-Dist: mutagen
Requires-Dist: simplejson
Requires-Dist: sqlalchemy
